teleme/__init__.py
teleme/_collections.py
teleme/_exceptions.py
teleme/_methods.py
teleme/_version.py
teleme/py.typed
teleme-0.2.0.dist-info/LICENSE
teleme-0.2.0.dist-info/WHEEL
teleme-0.2.0.dist-info/METADATA
teleme-0.2.0.dist-info/RECORD
