Metadata-Version: 2.1
Name: teleme
Version: 0.2.0
Summary: An async, super simple Telegram Bot framework.
Home-page: https://github.com/futursolo/teleme
License: Apache-2.0
Author: Kaede Hoshikawa
Author-email: futursolo@icloud.com
Requires-Python: >=3.7.1,<4.0.0
Classifier: License :: OSI Approved :: Apache Software License
Classifier: Operating System :: MacOS
Classifier: Operating System :: MacOS :: MacOS X
Classifier: Operating System :: Microsoft
Classifier: Operating System :: Microsoft :: Windows
Classifier: Operating System :: POSIX
Classifier: Operating System :: POSIX :: Linux
Classifier: Operating System :: Unix
Classifier: Programming Language :: Python
Classifier: Programming Language :: Python :: 3
Classifier: Programming Language :: Python :: 3 :: Only
Classifier: Programming Language :: Python :: 3.8
Classifier: Programming Language :: Python :: 3.9
Classifier: Programming Language :: Python :: Implementation :: CPython
Requires-Dist: hiyori (>=0.2,<0.3)
Requires-Dist: importlib-metadata (>=4.0.1,<5.0.0); python_version <= "3.7"
Project-URL: Repository, https://github.com/futursolo/teleme
